{
    "created_at": "Wed Jul 14 16:19:21 +0000 2021",
    "id": 1415345182073974788,
    "id_str": "1415345182073974788",
    "full_text": "RT @romerocaroperu: Fiscal\u00eda denuncia que los de Per\u00fa Libre ten\u00edan chat en el que luego de las elecciones les advirtieron q eliminaran mens\u2026",
    "truncated": false,
    "display_text_range": [
        0,
        140
    ],
    "entities": {
        "hashtags": [],
        "symbols": [],
        "user_mentions": [
            {
                "screen_name": "romerocaroperu",
                "name": "Manuel Romero Caro",
                "id": 1141456125306507264,
                "id_str": "1141456125306507264",
                "indices": [
                    3,
                    18
                ]
            }
        ],
        "urls": []
    },
    "metadata": {
        "iso_language_code": "es",
        "result_type": "recent"
    },
    "source": "<a href=\"http://twitter.com/download/iphone\" rel=\"nofollow\">Twitter for iPhone</a>",
    "in_reply_to_status_id": null,
    "in_reply_to_status_id_str": null,
    "in_reply_to_user_id": null,
    "in_reply_to_user_id_str": null,
    "in_reply_to_screen_name": null,
    "user": {
        "id": 1216709416319275009,
        "id_str": "1216709416319275009",
        "name": "harta de tanta Mier..a COMUNISTA...",
        "screen_name": "marmore99431483",
        "location": "",
        "description": "al Comunismo dile \u201cNO\u201d",
        "url": null,
        "entities": {
            "description": {
                "urls": []
            }
        },
        "protected": false,
        "followers_count": 173,
        "friends_count": 324,
        "listed_count": 0,
        "created_at": "Mon Jan 13 13:11:55 +0000 2020",
        "favourites_count": 26754,
        "utc_offset": null,
        "time_zone": null,
        "geo_enabled": false,
        "verified": false,
        "statuses_count": 41167,
        "lang": null,
        "contributors_enabled": false,
        "is_translator": false,
        "is_translation_enabled": false,
        "profile_background_color": "F5F8FA",
        "profile_background_image_url": null,
        "profile_background_image_url_https": null,
        "profile_background_tile": false,
        "profile_image_url": "http://pbs.twimg.com/profile_images/1250251539093925889/sHYs8Ixn_normal.jpg",
        "profile_image_url_https": "https://pbs.twimg.com/profile_images/1250251539093925889/sHYs8Ixn_normal.jpg",
        "profile_banner_url": "https://pbs.twimg.com/profile_banners/1216709416319275009/1586918171",
        "profile_link_color": "1DA1F2",
        "profile_sidebar_border_color": "C0DEED",
        "profile_sidebar_fill_color": "DDEEF6",
        "profile_text_color": "333333",
        "profile_use_background_image": true,
        "has_extended_profile": false,
        "default_profile": true,
        "default_profile_image": false,
        "following": false,
        "follow_request_sent": false,
        "notifications": false,
        "translator_type": "none",
        "withheld_in_countries": []
    },
    "geo": null,
    "coordinates": null,
    "place": null,
    "contributors": null,
    "retweeted_status": {
        "created_at": "Wed Jul 14 15:08:55 +0000 2021",
        "id": 1415327455406080002,
        "id_str": "1415327455406080002",
        "full_text": "Fiscal\u00eda denuncia que los de Per\u00fa Libre ten\u00edan chat en el que luego de las elecciones les advirtieron q eliminaran mensajes de material electoral. magistrada Valverde advertia: \"conforme podemos advertir de estos pantallazos , se\u00f1ora magistrada, se tienen diversos n\u00fameros(1/2) https://t.co/JouIuej92z",
        "truncated": false,
        "display_text_range": [
            0,
            277
        ],
        "entities": {
            "hashtags": [],
            "symbols": [],
            "user_mentions": [],
            "urls": [],
            "media": [
                {
                    "id": 1415324611126890496,
                    "id_str": "1415324611126890496",
                    "indices": [
                        278,
                        301
                    ],
                    "media_url": "http://pbs.twimg.com/media/E6Q-PDAWEAA4jDn.jpg",
                    "media_url_https": "https://pbs.twimg.com/media/E6Q-PDAWEAA4jDn.jpg",
                    "url": "https://t.co/JouIuej92z",
                    "display_url": "pic.twitter.com/JouIuej92z",
                    "expanded_url": "https://twitter.com/romerocaroperu/status/1415327455406080002/photo/1",
                    "type": "photo",
                    "sizes": {
                        "thumb": {
                            "w": 150,
                            "h": 150,
                            "resize": "crop"
                        },
                        "small": {
                            "w": 309,
                            "h": 359,
                            "resize": "fit"
                        },
                        "medium": {
                            "w": 309,
                            "h": 359,
                            "resize": "fit"
                        },
                        "large": {
                            "w": 309,
                            "h": 359,
                            "resize": "fit"
                        }
                    }
                }
            ]
        },
        "extended_entities": {
            "media": [
                {
                    "id": 1415324611126890496,
                    "id_str": "1415324611126890496",
                    "indices": [
                        278,
                        301
                    ],
                    "media_url": "http://pbs.twimg.com/media/E6Q-PDAWEAA4jDn.jpg",
                    "media_url_https": "https://pbs.twimg.com/media/E6Q-PDAWEAA4jDn.jpg",
                    "url": "https://t.co/JouIuej92z",
                    "display_url": "pic.twitter.com/JouIuej92z",
                    "expanded_url": "https://twitter.com/romerocaroperu/status/1415327455406080002/photo/1",
                    "type": "photo",
                    "sizes": {
                        "thumb": {
                            "w": 150,
                            "h": 150,
                            "resize": "crop"
                        },
                        "small": {
                            "w": 309,
                            "h": 359,
                            "resize": "fit"
                        },
                        "medium": {
                            "w": 309,
                            "h": 359,
                            "resize": "fit"
                        },
                        "large": {
                            "w": 309,
                            "h": 359,
                            "resize": "fit"
                        }
                    }
                }
            ]
        },
        "metadata": {
            "iso_language_code": "es",
            "result_type": "recent"
        },
        "source": "<a href=\"https://mobile.twitter.com\" rel=\"nofollow\">Twitter Web App</a>",
        "in_reply_to_status_id": null,
        "in_reply_to_status_id_str": null,
        "in_reply_to_user_id": null,
        "in_reply_to_user_id_str": null,
        "in_reply_to_screen_name": null,
        "user": {
            "id": 1141456125306507264,
            "id_str": "1141456125306507264",
            "name": "Manuel Romero Caro",
            "screen_name": "romerocaroperu",
            "location": "Lima, Peru",
            "description": "Economista independiente de grupos econ\u00f3micos y agrupaciones pol\u00edticas, que busca defender el inter\u00e9s publico y promover la libertad econ\u00f3mica y social.",
            "url": "https://t.co/HtTYlh5AsN",
            "entities": {
                "url": {
                    "urls": [
                        {
                            "url": "https://t.co/HtTYlh5AsN",
                            "expanded_url": "http://www.romerocaro.com",
                            "display_url": "romerocaro.com",
                            "indices": [
                                0,
                                23
                            ]
                        }
                    ]
                },
                "description": {
                    "urls": []
                }
            },
            "protected": false,
            "followers_count": 12298,
            "friends_count": 251,
            "listed_count": 28,
            "created_at": "Wed Jun 19 21:22:02 +0000 2019",
            "favourites_count": 38,
            "utc_offset": null,
            "time_zone": null,
            "geo_enabled": false,
            "verified": false,
            "statuses_count": 5244,
            "lang": null,
            "contributors_enabled": false,
            "is_translator": false,
            "is_translation_enabled": false,
            "profile_background_color": "F5F8FA",
            "profile_background_image_url": null,
            "profile_background_image_url_https": null,
            "profile_background_tile": false,
            "profile_image_url": "http://pbs.twimg.com/profile_images/1154565610711474176/mXaCOEoq_normal.jpg",
            "profile_image_url_https": "https://pbs.twimg.com/profile_images/1154565610711474176/mXaCOEoq_normal.jpg",
            "profile_banner_url": "https://pbs.twimg.com/profile_banners/1141456125306507264/1571180892",
            "profile_link_color": "1DA1F2",
            "profile_sidebar_border_color": "C0DEED",
            "profile_sidebar_fill_color": "DDEEF6",
            "profile_text_color": "333333",
            "profile_use_background_image": true,
            "has_extended_profile": false,
            "default_profile": true,
            "default_profile_image": false,
            "following": false,
            "follow_request_sent": false,
            "notifications": false,
            "translator_type": "none",
            "withheld_in_countries": []
        },
        "geo": null,
        "coordinates": null,
        "place": null,
        "contributors": null,
        "is_quote_status": false,
        "retweet_count": 30,
        "favorite_count": 51,
        "favorited": false,
        "retweeted": false,
        "possibly_sensitive": false,
        "lang": "es"
    },
    "is_quote_status": false,
    "retweet_count": 30,
    "favorite_count": 0,
    "favorited": false,
    "retweeted": false,
    "lang": "es"
}