{
    "created_at": "Mon Jul 12 17:07:54 +0000 2021",
    "id": 1414632621586403330,
    "id_str": "1414632621586403330",
    "full_text": "RT @TendenciaPe: \"Cavani\":\nPor las criticas hacia el 11 ideal de la #CopaAmerica y algunos usuarios piden que se reemplace al uruguayo Edin\u2026",
    "truncated": false,
    "display_text_range": [
        0,
        140
    ],
    "entities": {
        "hashtags": [
            {
                "text": "CopaAmerica",
                "indices": [
                    68,
                    80
                ]
            }
        ],
        "symbols": [],
        "user_mentions": [
            {
                "screen_name": "TendenciaPe",
                "name": "\u00bfPor qu\u00e9 es Tendencia_Pe?",
                "id": 1206683653939421187,
                "id_str": "1206683653939421187",
                "indices": [
                    3,
                    15
                ]
            }
        ],
        "urls": []
    },
    "metadata": {
        "iso_language_code": "es",
        "result_type": "recent"
    },
    "source": "<a href=\"https://mobile.twitter.com\" rel=\"nofollow\">Twitter Web App</a>",
    "in_reply_to_status_id": null,
    "in_reply_to_status_id_str": null,
    "in_reply_to_user_id": null,
    "in_reply_to_user_id_str": null,
    "in_reply_to_screen_name": null,
    "user": {
        "id": 32513017,
        "id_str": "32513017",
        "name": "\ud83c\uddf5\ud83c\uddea Javier Curay Tume",
        "screen_name": "franjavi",
        "location": "Piura",
        "description": "Abogado | @JuventudLac | Escritor | Fundador de @TintaDigitalx | Construyendo \ud83c\uddf5\ud83c\uddea con @IlidePeru y @Red_Interquorum | Activista @ProeticaPeru | Aliancista \ud83d\udc99",
        "url": "https://t.co/CX40CaOH5w",
        "entities": {
            "url": {
                "urls": [
                    {
                        "url": "https://t.co/CX40CaOH5w",
                        "expanded_url": "https://bitacoradeunescritor.art.blog/",
                        "display_url": "bitacoradeunescritor.art.blog",
                        "indices": [
                            0,
                            23
                        ]
                    }
                ]
            },
            "description": {
                "urls": []
            }
        },
        "protected": false,
        "followers_count": 861,
        "friends_count": 1785,
        "listed_count": 8,
        "created_at": "Fri Apr 17 18:32:52 +0000 2009",
        "favourites_count": 42987,
        "utc_offset": null,
        "time_zone": null,
        "geo_enabled": true,
        "verified": false,
        "statuses_count": 31737,
        "lang": null,
        "contributors_enabled": false,
        "is_translator": false,
        "is_translation_enabled": false,
        "profile_background_color": "000000",
        "profile_background_image_url": "http://abs.twimg.com/images/themes/theme14/bg.gif",
        "profile_background_image_url_https": "https://abs.twimg.com/images/themes/theme14/bg.gif",
        "profile_background_tile": false,
        "profile_image_url": "http://pbs.twimg.com/profile_images/1403182918722277382/4uUSOxoD_normal.jpg",
        "profile_image_url_https": "https://pbs.twimg.com/profile_images/1403182918722277382/4uUSOxoD_normal.jpg",
        "profile_banner_url": "https://pbs.twimg.com/profile_banners/32513017/1611263034",
        "profile_link_color": "000000",
        "profile_sidebar_border_color": "000000",
        "profile_sidebar_fill_color": "303030",
        "profile_text_color": "757575",
        "profile_use_background_image": true,
        "has_extended_profile": true,
        "default_profile": false,
        "default_profile_image": false,
        "following": false,
        "follow_request_sent": false,
        "notifications": false,
        "translator_type": "none",
        "withheld_in_countries": []
    },
    "geo": null,
    "coordinates": null,
    "place": null,
    "contributors": null,
    "retweeted_status": {
        "created_at": "Mon Jul 12 15:40:42 +0000 2021",
        "id": 1414610676992053250,
        "id_str": "1414610676992053250",
        "full_text": "\"Cavani\":\nPor las criticas hacia el 11 ideal de la #CopaAmerica y algunos usuarios piden que se reemplace al uruguayo Edinson Cavani con Gianluca Lapadula. https://t.co/MXwo7MxrU6",
        "truncated": false,
        "display_text_range": [
            0,
            155
        ],
        "entities": {
            "hashtags": [
                {
                    "text": "CopaAmerica",
                    "indices": [
                        51,
                        63
                    ]
                }
            ],
            "symbols": [],
            "user_mentions": [],
            "urls": [],
            "media": [
                {
                    "id": 1414610271801430022,
                    "id_str": "1414610271801430022",
                    "indices": [
                        156,
                        179
                    ],
                    "media_url": "http://pbs.twimg.com/media/E6G0jBpX0AYxSuU.jpg",
                    "media_url_https": "https://pbs.twimg.com/media/E6G0jBpX0AYxSuU.jpg",
                    "url": "https://t.co/MXwo7MxrU6",
                    "display_url": "pic.twitter.com/MXwo7MxrU6",
                    "expanded_url": "https://twitter.com/TendenciaPe/status/1414610676992053250/photo/1",
                    "type": "photo",
                    "sizes": {
                        "thumb": {
                            "w": 150,
                            "h": 150,
                            "resize": "crop"
                        },
                        "small": {
                            "w": 680,
                            "h": 680,
                            "resize": "fit"
                        },
                        "large": {
                            "w": 1280,
                            "h": 1280,
                            "resize": "fit"
                        },
                        "medium": {
                            "w": 1200,
                            "h": 1200,
                            "resize": "fit"
                        }
                    }
                }
            ]
        },
        "extended_entities": {
            "media": [
                {
                    "id": 1414610271801430022,
                    "id_str": "1414610271801430022",
                    "indices": [
                        156,
                        179
                    ],
                    "media_url": "http://pbs.twimg.com/media/E6G0jBpX0AYxSuU.jpg",
                    "media_url_https": "https://pbs.twimg.com/media/E6G0jBpX0AYxSuU.jpg",
                    "url": "https://t.co/MXwo7MxrU6",
                    "display_url": "pic.twitter.com/MXwo7MxrU6",
                    "expanded_url": "https://twitter.com/TendenciaPe/status/1414610676992053250/photo/1",
                    "type": "photo",
                    "sizes": {
                        "thumb": {
                            "w": 150,
                            "h": 150,
                            "resize": "crop"
                        },
                        "small": {
                            "w": 680,
                            "h": 680,
                            "resize": "fit"
                        },
                        "large": {
                            "w": 1280,
                            "h": 1280,
                            "resize": "fit"
                        },
                        "medium": {
                            "w": 1200,
                            "h": 1200,
                            "resize": "fit"
                        }
                    }
                }
            ]
        },
        "metadata": {
            "iso_language_code": "es",
            "result_type": "recent"
        },
        "source": "<a href=\"https://mobile.twitter.com\" rel=\"nofollow\">Twitter Web App</a>",
        "in_reply_to_status_id": null,
        "in_reply_to_status_id_str": null,
        "in_reply_to_user_id": null,
        "in_reply_to_user_id_str": null,
        "in_reply_to_screen_name": null,
        "user": {
            "id": 1206683653939421187,
            "id_str": "1206683653939421187",
            "name": "\u00bfPor qu\u00e9 es Tendencia_Pe?",
            "screen_name": "TendenciaPe",
            "location": "Tendencias-Peru",
            "description": "Conoce el porqu\u00e9 de las tendencias en #TwitterPeru\nCuenta de respaldo: @TendenciaPe1",
            "url": null,
            "entities": {
                "description": {
                    "urls": []
                }
            },
            "protected": false,
            "followers_count": 24290,
            "friends_count": 24,
            "listed_count": 36,
            "created_at": "Mon Dec 16 21:13:28 +0000 2019",
            "favourites_count": 2293,
            "utc_offset": null,
            "time_zone": null,
            "geo_enabled": false,
            "verified": false,
            "statuses_count": 5350,
            "lang": null,
            "contributors_enabled": false,
            "is_translator": false,
            "is_translation_enabled": false,
            "profile_background_color": "F5F8FA",
            "profile_background_image_url": null,
            "profile_background_image_url_https": null,
            "profile_background_tile": false,
            "profile_image_url": "http://pbs.twimg.com/profile_images/1397647649881350148/ZKudAEX8_normal.jpg",
            "profile_image_url_https": "https://pbs.twimg.com/profile_images/1397647649881350148/ZKudAEX8_normal.jpg",
            "profile_banner_url": "https://pbs.twimg.com/profile_banners/1206683653939421187/1596658867",
            "profile_link_color": "1DA1F2",
            "profile_sidebar_border_color": "C0DEED",
            "profile_sidebar_fill_color": "DDEEF6",
            "profile_text_color": "333333",
            "profile_use_background_image": true,
            "has_extended_profile": true,
            "default_profile": true,
            "default_profile_image": false,
            "following": false,
            "follow_request_sent": false,
            "notifications": false,
            "translator_type": "none",
            "withheld_in_countries": []
        },
        "geo": null,
        "coordinates": null,
        "place": null,
        "contributors": null,
        "is_quote_status": false,
        "retweet_count": 21,
        "favorite_count": 266,
        "favorited": false,
        "retweeted": false,
        "possibly_sensitive": false,
        "lang": "es"
    },
    "is_quote_status": false,
    "retweet_count": 21,
    "favorite_count": 0,
    "favorited": false,
    "retweeted": false,
    "lang": "es"
}