{
    "created_at": "Mon Jul 12 05:17:32 +0000 2021",
    "id": 1414453852766625793,
    "id_str": "1414453852766625793",
    "full_text": "@ManagerTactical Por qu\u00e9 a Estados Unidos si le dejan traer su equipo c y descansar a sus estrellas y a mexico le obligan a traer su equipo A",
    "truncated": false,
    "display_text_range": [
        17,
        141
    ],
    "entities": {
        "hashtags": [],
        "symbols": [],
        "user_mentions": [
            {
                "screen_name": "ManagerTactical",
                "name": "Tactical Manager",
                "id": 1291557521023471616,
                "id_str": "1291557521023471616",
                "indices": [
                    0,
                    16
                ]
            }
        ],
        "urls": []
    },
    "metadata": {
        "iso_language_code": "es",
        "result_type": "recent"
    },
    "source": "<a href=\"http://twitter.com/download/iphone\" rel=\"nofollow\">Twitter for iPhone</a>",
    "in_reply_to_status_id": 1414446196115054593,
    "in_reply_to_status_id_str": "1414446196115054593",
    "in_reply_to_user_id": 1291557521023471616,
    "in_reply_to_user_id_str": "1291557521023471616",
    "in_reply_to_screen_name": "ManagerTactical",
    "user": {
        "id": 797320396014059520,
        "id_str": "797320396014059520",
        "name": "MTY",
        "screen_name": "MonterreyFC1",
        "location": "En el Olimpo ",
        "description": "Campeonatos de @Rayados \u2b50\u2b50\u2b50\u2b50\u2b50/\u2b50\u2b50\u2b50\ud83c\udf1f/\ud83c\udfc6 \u00a1ARRIBA EL GLORIOSO F\u00daTBOL CLUB MONTERREY! 01/05/19",
        "url": null,
        "entities": {
            "description": {
                "urls": []
            }
        },
        "protected": false,
        "followers_count": 127,
        "friends_count": 260,
        "listed_count": 0,
        "created_at": "Sat Nov 12 06:09:30 +0000 2016",
        "favourites_count": 24816,
        "utc_offset": null,
        "time_zone": null,
        "geo_enabled": false,
        "verified": false,
        "statuses_count": 3984,
        "lang": null,
        "contributors_enabled": false,
        "is_translator": false,
        "is_translation_enabled": false,
        "profile_background_color": "000000",
        "profile_background_image_url": "http://abs.twimg.com/images/themes/theme1/bg.png",
        "profile_background_image_url_https": "https://abs.twimg.com/images/themes/theme1/bg.png",
        "profile_background_tile": false,
        "profile_image_url": "http://pbs.twimg.com/profile_images/1398194718832484352/nhQMF5w0_normal.jpg",
        "profile_image_url_https": "https://pbs.twimg.com/profile_images/1398194718832484352/nhQMF5w0_normal.jpg",
        "profile_banner_url": "https://pbs.twimg.com/profile_banners/797320396014059520/1604772420",
        "profile_link_color": "ABB8C2",
        "profile_sidebar_border_color": "000000",
        "profile_sidebar_fill_color": "000000",
        "profile_text_color": "000000",
        "profile_use_background_image": false,
        "has_extended_profile": false,
        "default_profile": false,
        "default_profile_image": false,
        "following": false,
        "follow_request_sent": false,
        "notifications": false,
        "translator_type": "none",
        "withheld_in_countries": []
    },
    "geo": null,
    "coordinates": null,
    "place": null,
    "contributors": null,
    "is_quote_status": false,
    "retweet_count": 0,
    "favorite_count": 0,
    "favorited": false,
    "retweeted": false,
    "lang": "es"
}